stfile/__init__.py
stfile/command_line.py
stfile/config.yml
stfile/helpers.py
stfile/agents/__init__.py
stfile/agents/file_format.py
stfile/agents/movies.py
stfile/ontologies/catalog-v001.xml
stfile/ontologies/file_system.owl
stfile-0.1.dist-info/METADATA
stfile-0.1.dist-info/RECORD
stfile-0.1.dist-info/WHEEL
stfile-0.1.dist-info/entry_points.txt
stfile-0.1.dist-info/top_level.txt
