Metadata-Version: 2.1
Name: stfile
Version: 0.1
Summary: File System with semantics
Home-page: https://github.com/pabloriutort/stfile
Author: Pablo Riutort
Author-email: pablo.riutort@gmail.com
License: MIT
Keywords: semantics file system RDF OWL
Platform: UNKNOWN
Classifier: Programming Language :: Python
